boofun/__init__.py
boofun/api.py
boofun/py.typed
boofun/analysis/__init__.py
boofun/analysis/arrow.py
boofun/analysis/basic_properties.py
boofun/analysis/block_sensitivity.py
boofun/analysis/canalization.py
boofun/analysis/certificates.py
boofun/analysis/communication_complexity.py
boofun/analysis/complexity.py
boofun/analysis/cryptographic.py
boofun/analysis/decision_trees.py
boofun/analysis/equivalence.py
boofun/analysis/fkn.py
boofun/analysis/fourier.py
boofun/analysis/gaussian.py
boofun/analysis/gf2.py
boofun/analysis/global_hypercontractivity.py
boofun/analysis/huang.py
boofun/analysis/hypercontractivity.py
boofun/analysis/invariance.py
boofun/analysis/learning.py
boofun/analysis/ltf_analysis.py
boofun/analysis/p_biased.py
boofun/analysis/pac_learning.py
boofun/analysis/query_complexity.py
boofun/analysis/restrictions.py
boofun/analysis/sampling.py
boofun/analysis/sensitivity.py
boofun/analysis/sparsity.py
boofun/analysis/symmetry.py
boofun/benchmarks/__init__.py
boofun/core/__init__.py
boofun/core/adapters.py
boofun/core/auto_representation.py
boofun/core/base.py
boofun/core/batch_processing.py
boofun/core/builtins.py
boofun/core/conversion_graph.py
boofun/core/errormodels.py
boofun/core/factory.py
boofun/core/gpu.py
boofun/core/gpu_acceleration.py
boofun/core/io.py
boofun/core/legacy_adapter.py
boofun/core/numba_optimizations.py
boofun/core/optimizations.py
boofun/core/partial.py
boofun/core/query_model.py
boofun/core/spaces.py
boofun/core/representations/__init__.py
boofun/core/representations/anf_form.py
boofun/core/representations/base.py
boofun/core/representations/bdd.py
boofun/core/representations/circuit.py
boofun/core/representations/cnf_form.py
boofun/core/representations/distribution.py
boofun/core/representations/dnf_form.py
boofun/core/representations/fourier_expansion.py
boofun/core/representations/ltf.py
boofun/core/representations/packed_truth_table.py
boofun/core/representations/polynomial.py
boofun/core/representations/registry.py
boofun-1.1.1.dist-info/licenses/LICENSE
boofun-1.1.1.dist-info/METADATA
boofun-1.1.1.dist-info/WHEEL
boofun-1.1.1.dist-info/top_level.txt
boofun-1.1.1.dist-info/RECORD
