Metadata-Version: 2.4
Name: boofun
Version: 1.1.1
Summary: A Python library for Boolean function analysis and spectral methods
Author-email: Gabriel Taboada <gabtab@berkeley.edu>
License: MIT
Project-URL: Homepage, https://github.com/GabbyTab/boofun
Project-URL: Repository, https://github.com/GabbyTab/boofun
Project-URL: Issues, https://github.com/GabbyTab/boofun/issues
Keywords: boolean-functions,fourier-analysis,spectral-analysis,property-testing
Classifier: Development Status :: 4 - Beta
Classifier: Intended Audience :: Science/Research
Classifier: License :: OSI Approved :: MIT License
Classifier: Programming Language :: Python :: 3
Classifier: Programming Language :: Python :: 3.8
Classifier: Programming Language :: Python :: 3.9
Classifier: Programming Language :: Python :: 3.10
Classifier: Programming Language :: Python :: 3.11
Classifier: Programming Language :: Python :: 3.12
Classifier: Topic :: Scientific/Engineering :: Mathematics
Classifier: Operating System :: OS Independent
Requires-Python: >=3.8
License-File: LICENSE
Requires-Dist: numpy>=1.20.0
Requires-Dist: scipy>=1.7.0
Requires-Dist: numba>=0.56.0
Provides-Extra: performance
Requires-Dist: bitarray>=2.8.0; extra == "performance"
Provides-Extra: gpu
Requires-Dist: pyfwht>=0.2.0; extra == "gpu"
Provides-Extra: visualization
Requires-Dist: matplotlib>=3.5.0; extra == "visualization"
Requires-Dist: plotly>=5.0.0; extra == "visualization"
Provides-Extra: docs
Requires-Dist: sphinx>=5.0.0; extra == "docs"
Requires-Dist: sphinx-rtd-theme>=1.0.0; extra == "docs"
Requires-Dist: myst-parser>=0.18.0; extra == "docs"
Requires-Dist: sphinx-autodoc-typehints>=1.19.0; extra == "docs"
Provides-Extra: dev
Requires-Dist: pytest>=7.0.0; extra == "dev"
Requires-Dist: pytest-cov>=4.0.0; extra == "dev"
Requires-Dist: pytest-benchmark>=4.0.0; extra == "dev"
Requires-Dist: black>=22.0.0; extra == "dev"
Requires-Dist: flake8>=5.0.0; extra == "dev"
Requires-Dist: mypy>=1.0.0; extra == "dev"
Requires-Dist: pre-commit>=3.0.0; extra == "dev"
Requires-Dist: isort>=5.12.0; extra == "dev"
Requires-Dist: mutmut>=2.4.0; extra == "dev"
Requires-Dist: hypothesis>=6.0.0; extra == "dev"
Provides-Extra: all
Requires-Dist: boofun[dev,docs,gpu,performance,visualization]; extra == "all"
Dynamic: license-file
